README.txt
setup.py
docs/HISTORY.txt
redturtle/__init__.py
redturtle.maps.core.egg-info/PKG-INFO
redturtle.maps.core.egg-info/SOURCES.txt
redturtle.maps.core.egg-info/dependency_links.txt
redturtle.maps.core.egg-info/entry_points.txt
redturtle.maps.core.egg-info/namespace_packages.txt
redturtle.maps.core.egg-info/not-zip-safe
redturtle.maps.core.egg-info/requires.txt
redturtle.maps.core.egg-info/top_level.txt
redturtle/maps/__init__.py
redturtle/maps/core/__init__.py
redturtle/maps/core/adapter.py
redturtle/maps/core/config.py
redturtle/maps/core/configure.zcml
redturtle/maps/core/profiles.zcml
redturtle/maps/core/skins.zcml
redturtle/maps/core/browser/__init__.py
redturtle/maps/core/browser/base.pt
redturtle/maps/core/browser/base.py
redturtle/maps/core/browser/base_event.pt
redturtle/maps/core/browser/base_file.pt
redturtle/maps/core/browser/base_image.pt
redturtle/maps/core/browser/base_link.pt
redturtle/maps/core/browser/base_newsitem.pt
redturtle/maps/core/browser/configure.zcml
redturtle/maps/core/browser/search.py
redturtle/maps/core/browser/search_results.pt
redturtle/maps/core/profiles/default/metadata.xml
redturtle/maps/core/profiles/default/skins.xml
redturtle/maps/core/skins/redturtle_maps_core/maps-googlemaps.js
redturtle/maps/core/skins/redturtle_maps_core/maps_map.pt
redturtle/maps/core/skins/redturtle_maps_core/maps_map.pt.metadata
redturtle/maps/core/tests/__init__.py
redturtle/maps/core/tests/test_doctests.py