Metadata-Version: 1.0
Name: redturtle.maps.core
Version: 0.2.1
Summary: Every plone contents can be drawn on a Maps'map
Home-page: http://plone.org/products/redturtle-maps.core
Author: Andrew Mleczko, Massimo Azzolini, Luca Fabbri
Author-email: massimo@redturtle.net
License: GPL
Keywords: maps contents plone
Platform: UNKNOWN
Classifier: Programming Language :: Python
Classifier: Topic :: Software Development :: Libraries :: Python Modules
Classifier: Framework :: Plone
